Workbook
Name aporte: 'Calculadora de Investimento'!$D$19
Name patrimonio: 'Calculadora de Investimento'!$D$22
Name qtd_anos: 'Calculadora de Investimento'!$D$20
Name rendimento_carteira: 'Calculadora de Investimento'!$D$14
Name salario: 'Calculadora de Investimento'!$D$13
Name sugestao_investimento: 'Calculadora de Investimento'!$D$15
Name taxa_mensal: 'Calculadora de Investimento'!$D$21

Sheet Calculadora de Investimento
B12: CONFIGURAÇÕES
B13: Salário | D13: 4200
B14: Rendimento Carteira | D14: 0.006
B15: Sugestão de Investimento (30%) | D15: =D13*30% -> 1260
B18: INVESTIMENTO MENSAL
B19: Quanto investir por mês? | D19: 1260
B20: Por quantos anos? | D20: 10
B21: Taxa de rendimento mensal? | D21: 0.01079
B22: Patrimônio Acumulado? | D22: =FV(taxa_mensal,qtd_anos*12,aporte*-1) -> 306538.11
B23: Dividendos mensais? | D23: =patrimonio*0.6% -> 1839.2286
B25: Cenários | D25: Dividendos
A26: 2 | B26: Quanto em 2 anos? | C26: =FV($D$21,$A26*12,$D$19*-1) -> 34306.81 | D26: =C26*rendimento_carteira -> 205.84086
A27: 5 | B27: Quanto em 5 anos? | C27: =FV($D$21,$A27*12,$D$19*-1) -> 105558.91 | D27: =C27*rendimento_carteira -> 633.35347
A28: 10 | B28: Quanto em 10 anos? | C28: =FV($D$21,$A28*12,$D$19*-1) -> 306538.11 | D28: =C28*rendimento_carteira -> 1839.2286
A29: 20 | B29: Quanto em 20 anos? | C29: =FV($D$21,$A29*12,$D$19*-1) -> 1417750 | D29: =C29*rendimento_carteira -> 8506.4999
A30: 30 | B30: Quanto em 30 anos? | C30: =FV($D$21,$A30*12,$D$19*-1) -> 5445933.8 | D30: =C30*rendimento_carteira -> 32675.603
B32: Perfil | C32: Conservador
B33: Valor Mensal Investido | C33: =aporte -> 1260
B35: Tipo de FII | C35: Percentual Sugerido | D35: Valores
B36: PAPEL | C36: =VLOOKUP($C$32&"-"&B36,Planilha2!A:D,4,FALSE) -> 0.3 | D36: =C36*$C$33 -> 378
B37: TIJOLO | C37: =VLOOKUP($C$32&"-"&B37,Planilha2!A:D,4,FALSE) -> 0.5 | D37: =C37*$C$33 -> 630
B38: HÍBRIDOS | C38: =VLOOKUP($C$32&"-"&B38,Planilha2!A:D,4,FALSE) -> 0.1 | D38: =C38*$C$33 -> 126
B39: FOFs | C39: =VLOOKUP($C$32&"-"&B39,Planilha2!A:D,4,FALSE) -> 0.1 | D39: =C39*$C$33 -> 126
B40: DESENVOLVIMENTO | C40: =VLOOKUP($C$32&"-"&B40,Planilha2!A:D,4,FALSE) -> 0 | D40: =C40*$C$33 -> 0
B41: HOTELARIAS | C41: =VLOOKUP($C$32&"-"&B41,Planilha2!A:D,4,FALSE) -> 0 | D41: =C41*$C$33 -> 0
D42: =SUM(D36:D41) -> 1260

Sheet Planilha2
A2: Chave | B2: PERFIL | C2: Tipo de FII | D2: %
A3: =B3&"-"&C3 -> Conservador-PAPEL | B3: Conservador | C3: PAPEL | D3: 0.3 | G3: %
A4: =B4&"-"&C4 -> Conservador-TIJOLO | B4: Conservador | C4: TIJOLO | D4: 0.5 | F4: Moderado-TIJOLO | G4: =VLOOKUP(F4,$A$3:$D$20,4,FALSE) -> 0.35
A5: =B5&"-"&C5 -> Conservador-HÍBRIDOS | B5: Conservador | C5: HÍBRIDOS | D5: 0.1
A6: =B6&"-"&C6 -> Conservador-FOFs | B6: Conservador | C6: FOFs | D6: 0.1
A7: =B7&"-"&C7 -> Conservador-DESENVOLVIMENTO | B7: Conservador | C7: DESENVOLVIMENTO | D7: 0
A8: =B8&"-"&C8 -> Conservador-HOTELARIAS | B8: Conservador | C8: HOTELARIAS | D8: 0
A9: =B9&"-"&C9 -> Moderado-PAPEL | B9: Moderado | C9: PAPEL | D9: 0.32
A10: =B10&"-"&C10 -> Moderado-TIJOLO | B10: Moderado | C10: TIJOLO | D10: 0.35
A11: =B11&"-"&C11 -> Moderado-HÍBRIDOS | B11: Moderado | C11: HÍBRIDOS | D11: 0.08
A12: =B12&"-"&C12 -> Moderado-FOFs | B12: Moderado | C12: FOFs | D12: 0.05
A13: =B13&"-"&C13 -> Moderado-DESENVOLVIMENTO | B13: Moderado | C13: DESENVOLVIMENTO | D13: 0.1
A14: =B14&"-"&C14 -> Moderado-HOTELARIAS | B14: Moderado | C14: HOTELARIAS | D14: 0.1
A15: =B15&"-"&C15 -> Agressivo-PAPEL | B15: Agressivo | C15: PAPEL | D15: 0.5
A16: =B16&"-"&C16 -> Agressivo-TIJOLO | B16: Agressivo | C16: TIJOLO | D16: 0.1
... A20: =B20&"-"&C20 -> Agressivo-HOTELARIAS | B20: Agressivo | C20: HOTELARIAS | D20: 0.1
